arc_adaptors/__init__.py
arc_adaptors/base.py
arc_adaptors/anthropic/__init__.py
arc_adaptors/langchain/__init__.py
arc_adaptors/langchain/adaptor.py
arc_adaptors/langchain/client.py
arc_adaptors/langchain/tools.py
arc_adaptors/llama_index/__init__.py
arc_adaptors/mistral/__init__.py
arc_adaptors/openai/__init__.py
arc_adaptors-0.1.0.dist-info/licenses/LICENSE
tests/__init__.py
tests/test_base.py
tests/test_langchain_adaptor.py
arc_adaptors-0.1.0.dist-info/METADATA
arc_adaptors-0.1.0.dist-info/WHEEL
arc_adaptors-0.1.0.dist-info/top_level.txt
arc_adaptors-0.1.0.dist-info/RECORD
